speedracer/__init__.py
speedracer-0.0.12.dist-info/METADATA
speedracer-0.0.12.dist-info/WHEEL
speedracer-0.0.12.dist-info/licenses/LICENSE
speedracer-0.0.12.dist-info/RECORD
