Metadata-Version: 2.4
Name: speedracer
Version: 0.0.12
Summary: Conveniently access data
Author: RRC
License-File: LICENSE
Classifier: License :: OSI Approved :: MIT License
Classifier: Operating System :: POSIX :: Linux
Classifier: Programming Language :: Python :: 3
Requires-Python: >=3.8
Requires-Dist: aiohttp<4.0.0,>=3.8.4
Requires-Dist: nats-py[nkeys]~=2.10.0
Requires-Dist: pyjwt<3.0.0,>=2.7.0
Requires-Dist: requests<3.0.0,>=2.31.0
